hypo_schema/__init__.py
hypo_schema/hypo_schema.py
hypo_schema/regex.py
hypo_schema-0.2.1.dist-info/DESCRIPTION.rst
hypo_schema-0.2.1.dist-info/METADATA
hypo_schema-0.2.1.dist-info/RECORD
hypo_schema-0.2.1.dist-info/WHEEL
hypo_schema-0.2.1.dist-info/metadata.json
hypo_schema-0.2.1.dist-info/top_level.txt
